crossword_puzzle
dist
docs
pdf_examples
